{"pr_number": 1563, "pr_title": "LUCENE-9394: fix and suppress warnings", "pr_createdAt": "2020-06-10T11:27:08Z", "pr_url": "https://github.com/apache/lucene-solr/pull/1563", "timeline": [{"oid": "49be796e8fe086226d16eb5e5bdf3314a8266a27", "url": "https://github.com/apache/lucene-solr/commit/49be796e8fe086226d16eb5e5bdf3314a8266a27", "message": "LUCENE-9394: fix and suppress warnings", "committedDate": "2020-06-10T11:25:35Z", "type": "commit"}, {"oid": "8d03bc1c6fe04264d4274d6204f7843c09f98c32", "url": "https://github.com/apache/lucene-solr/commit/8d03bc1c6fe04264d4274d6204f7843c09f98c32", "message": "a few cosmetic issues", "committedDate": "2020-06-10T11:36:42Z", "type": "commit"}, {"oid": "b55c52028ecb5867a9d0cfc3880682257a66c271", "url": "https://github.com/apache/lucene-solr/commit/b55c52028ecb5867a9d0cfc3880682257a66c271", "message": "Change type of ValuesSource context from raw Map to Map<Object, Object>", "committedDate": "2020-06-10T14:54:23Z", "type": "commit"}, {"oid": "87317c83c6047828976d09268465b1b190855557", "url": "https://github.com/apache/lucene-solr/commit/87317c83c6047828976d09268465b1b190855557", "message": "A few more raw Map -> Map<Object, Object>", "committedDate": "2020-06-10T16:36:01Z", "type": "commit"}, {"id": "MDI0OlB1bGxSZXF1ZXN0UmV2aWV3Q29tbWVudDQzODk3NTczMA==", "url": "https://github.com/apache/lucene-solr/pull/1563#discussion_r438975730", "bodyText": "Add a comment that we're explicitly avoiding the Integer cache, and an assertNotSame(val, val1)?", "author": "madrob", "createdAt": "2020-06-11T18:04:24Z", "path": "lucene/core/src/test/org/apache/lucene/analysis/TestCharArraySet.java", "diffHunk": "@@ -61,15 +61,17 @@ public void testNonZeroOffset() {\n   public void testObjectContains() {\n     CharArraySet set = new CharArraySet(10, true);\n     Integer val = Integer.valueOf(1);\n+    @SuppressWarnings(\"deprecation\")\n+    Integer val1 = new Integer(1);", "originalCommit": "87317c83c6047828976d09268465b1b190855557", "replyToReviewId": null, "replies": null, "type": "inlineReview"}, {"id": "MDI0OlB1bGxSZXF1ZXN0UmV2aWV3Q29tbWVudDQzODk4MjkyNw==", "url": "https://github.com/apache/lucene-solr/pull/1563#discussion_r438982927", "bodyText": "wildcard import", "author": "madrob", "createdAt": "2020-06-11T18:17:43Z", "path": "lucene/spatial-extras/src/test/org/apache/lucene/spatial/prefix/HeatmapFacetCounterTest.java", "diffHunk": "@@ -33,11 +33,7 @@\n import org.locationtech.spatial4j.context.SpatialContext;\n import org.locationtech.spatial4j.context.SpatialContextFactory;\n import org.locationtech.spatial4j.distance.DistanceUtils;\n-import org.locationtech.spatial4j.shape.Circle;\n-import org.locationtech.spatial4j.shape.Point;\n-import org.locationtech.spatial4j.shape.Rectangle;\n-import org.locationtech.spatial4j.shape.Shape;\n-import org.locationtech.spatial4j.shape.SpatialRelation;\n+import org.locationtech.spatial4j.shape.*;", "originalCommit": "87317c83c6047828976d09268465b1b190855557", "replyToReviewId": null, "replies": null, "type": "inlineReview"}, {"id": "MDI0OlB1bGxSZXF1ZXN0UmV2aWV3Q29tbWVudDQzODk4NDA4NQ==", "url": "https://github.com/apache/lucene-solr/pull/1563#discussion_r438984085", "bodyText": "There appear to be more unused methods in this class, why did we keep them but not these?", "author": "madrob", "createdAt": "2020-06-11T18:19:58Z", "path": "lucene/spatial-extras/src/test/org/apache/lucene/spatial/spatial4j/RandomizedShapeTestCase.java", "diffHunk": "@@ -183,106 +179,4 @@ private void _assertIntersect(String msg, SpatialRelation expected, Shape a, Sha\n     }\n   }\n \n-  protected void assertEqualsRatio(String msg, double expected, double actual) {", "originalCommit": "87317c83c6047828976d09268465b1b190855557", "replyToReviewId": null, "replies": null, "type": "inlineReview"}, {"oid": "109075e280da8f02f5af0182e4684393c1b6a55f", "url": "https://github.com/apache/lucene-solr/commit/109075e280da8f02f5af0182e4684393c1b6a55f", "message": "Address PR comments", "committedDate": "2020-06-11T19:31:22Z", "type": "commit"}]}