{"data": {"search": {"issueCount": 29, "pageInfo": {"startCursor": "Y3Vyc29yOjE=", "endCursor": "Y3Vyc29yOjI5", "hasNextPage": false, "hasPreviousPage": false}, "nodes": [{"id": "MDExOlB1bGxSZXF1ZXN0NzMxMTAwMzQ4", "number": 81, "title": "[ jpms ] module-info.java", "createdAt": "2021-09-10T02:02:44Z", "url": "https://github.com/ice1000/jimgui/pull/81", "merged": false, "comments": {"totalCount": 0}, "reviews": {"totalCount": 0}, "reviewRequests": {"totalCount": 0}, "timelineItems": {"totalCount": 0, "pageInfo": {"startCursor": null, "endCursor": null, "hasNextPage": false, "hasPreviousPage": false}, "nodes": []}}, {"id": "MDExOlB1bGxSZXF1ZXN0NzMwNjI3MTYz", "number": 80, "title": "Improve cross platform support", "createdAt": "2021-09-09T14:05:19Z", "url": "https://github.com/ice1000/jimgui/pull/80", "merged": true, "comments": {"totalCount": 8}, "reviews": {"totalCount": 0}, "reviewRequests": {"totalCount": 0}, "timelineItems": {"totalCount": 0, "pageInfo": {"startCursor": null, "endCursor": null, "hasNextPage": false, "hasPreviousPage": false}, "nodes": []}}, {"id": "MDExOlB1bGxSZXF1ZXN0NTk4NjM2NDE2", "number": 76, "title": "Support Apple Silicon", "createdAt": "2021-03-23T07:59:49Z", "url": "https://github.com/ice1000/jimgui/pull/76", "merged": true, "comments": {"totalCount": 1}, "reviews": {"totalCount": 0}, "reviewRequests": {"totalCount": 1}, "timelineItems": {"totalCount": 0, "pageInfo": {"startCursor": null, "endCursor": null, "hasNextPage": false, "hasPreviousPage": false}, "nodes": []}}, {"id": "MDExOlB1bGxSZXF1ZXN0NTQwOTkyNzc3", "number": 72, "title": "File dialog", "createdAt": "2020-12-16T08:41:23Z", "url": "https://github.com/ice1000/jimgui/pull/72", "merged": true, "comments": {"totalCount": 0}, "reviews": {"totalCount": 0}, "reviewRequests": {"totalCount": 0}, "timelineItems": {"totalCount": 0, "pageInfo": {"startCursor": null, "endCursor": null, "hasNextPage": false, "hasPreviousPage": false}, "nodes": []}}, {"id": "MDExOlB1bGxSZXF1ZXN0NTM5MDgxMzk2", "number": 70, "title": "inputText, inputTextMultiline and inputTextWithHint", "createdAt": "2020-12-14T02:19:07Z", "url": "https://github.com/ice1000/jimgui/pull/70", "merged": true, "comments": {"totalCount": 0}, "reviews": {"totalCount": 0}, "reviewRequests": {"totalCount": 1}, "timelineItems": {"totalCount": 0, "pageInfo": {"startCursor": null, "endCursor": null, "hasNextPage": false, "hasPreviousPage": false}, "nodes": []}}, {"id": "MDExOlB1bGxSZXF1ZXN0NTI1Mjc5NTYy", "number": 63, "title": "[ doc ] Improve MACos description", "createdAt": "2020-11-22T12:57:24Z", "url": "https://github.com/ice1000/jimgui/pull/63", "merged": true, "comments": {"totalCount": 0}, "reviews": {"totalCount": 0}, "reviewRequests": {"totalCount": 0}, "timelineItems": {"totalCount": 0, "pageInfo": {"startCursor": null, "endCursor": null, "hasNextPage": false, "hasPreviousPage": false}, "nodes": []}}, {"id": "MDExOlB1bGxSZXF1ZXN0NTIxMDQyNzIz", "number": 62, "title": "rename TabMinWidthForUnselectedCloseButton to TabMinWidthForCloseButton", "createdAt": "2020-11-14T18:25:58Z", "url": "https://github.com/ice1000/jimgui/pull/62", "merged": true, "comments": {"totalCount": 0}, "reviews": {"totalCount": 1}, "reviewRequests": {"totalCount": 0}, "timelineItems": {"totalCount": 1, "pageInfo": {"startCursor": "Y3Vyc29yOnYyOpPPAAABdcyGEmAFqTUzMDgwODgzMw==", "endCursor": "Y3Vyc29yOnYyOpPPAAABdcyGEmAFqTUzMDgwODgzMw==", "hasNextPage": false, "hasPreviousPage": false}, "nodes": [{"comments": {"totalCount": 0}}]}}, {"id": "MDExOlB1bGxSZXF1ZXN0NTIxMDQyMTQ2", "number": 61, "title": "rename ConfigWindowsMemoryCompactTimer to ConfigMemoryCompactTimer", "createdAt": "2020-11-14T18:21:18Z", "url": "https://github.com/ice1000/jimgui/pull/61", "merged": true, "comments": {"totalCount": 0}, "reviews": {"totalCount": 1}, "reviewRequests": {"totalCount": 0}, "timelineItems": {"totalCount": 1, "pageInfo": {"startCursor": "Y3Vyc29yOnYyOpPPAAABdcyFpQAFqTUzMDgwODc5MA==", "endCursor": "Y3Vyc29yOnYyOpPPAAABdcyFpQAFqTUzMDgwODc5MA==", "hasNextPage": false, "hasPreviousPage": false}, "nodes": [{"comments": {"totalCount": 0}}]}}, {"id": "MDExOlB1bGxSZXF1ZXN0NTIxMDQxNzA4", "number": 60, "title": "change build to fetch imgui from latest repo link", "createdAt": "2020-11-14T18:17:30Z", "url": "https://github.com/ice1000/jimgui/pull/60", "merged": true, "comments": {"totalCount": 1}, "reviews": {"totalCount": 0}, "reviewRequests": {"totalCount": 0}, "timelineItems": {"totalCount": 0, "pageInfo": {"startCursor": null, "endCursor": null, "hasNextPage": false, "hasPreviousPage": false}, "nodes": []}}, {"id": "MDExOlB1bGxSZXF1ZXN0NDkwNjAxNzUz", "number": 57, "title": "Fix typo in readme", "createdAt": "2020-09-21T22:56:18Z", "url": "https://github.com/ice1000/jimgui/pull/57", "merged": true, "comments": {"totalCount": 0}, "reviews": {"totalCount": 0}, "reviewRequests": {"totalCount": 0}, "timelineItems": {"totalCount": 0, "pageInfo": {"startCursor": null, "endCursor": null, "hasNextPage": false, "hasPreviousPage": false}, "nodes": []}}, {"id": "MDExOlB1bGxSZXF1ZXN0NDkwMzQyMTI2", "number": 56, "title": "Add \"Automatic-Module-Name\" to gradle.build.kt", "createdAt": "2020-09-21T14:32:08Z", "url": "https://github.com/ice1000/jimgui/pull/56", "merged": true, "comments": {"totalCount": 23}, "reviews": {"totalCount": 0}, "reviewRequests": {"totalCount": 0}, "timelineItems": {"totalCount": 0, "pageInfo": {"startCursor": null, "endCursor": null, "hasNextPage": false, "hasPreviousPage": false}, "nodes": []}}, {"id": "MDExOlB1bGxSZXF1ZXN0NDkwMjc4MTY5", "number": 54, "title": "Add info regarding how to include using maven", "createdAt": "2020-09-21T12:57:12Z", "url": "https://github.com/ice1000/jimgui/pull/54", "merged": true, "comments": {"totalCount": 2}, "reviews": {"totalCount": 0}, "reviewRequests": {"totalCount": 0}, "timelineItems": {"totalCount": 0, "pageInfo": {"startCursor": null, "endCursor": null, "hasNextPage": false, "hasPreviousPage": false}, "nodes": []}}, {"id": "MDExOlB1bGxSZXF1ZXN0MzQ3MTcyNzky", "number": 50, "title": "Update README.md", "createdAt": "2019-11-29T23:07:44Z", "url": "https://github.com/ice1000/jimgui/pull/50", "merged": true, "comments": {"totalCount": 0}, "reviews": {"totalCount": 0}, "reviewRequests": {"totalCount": 0}, "timelineItems": {"totalCount": 0, "pageInfo": {"startCursor": null, "endCursor": null, "hasNextPage": false, "hasPreviousPage": false}, "nodes": []}}, {"id": "MDExOlB1bGxSZXF1ZXN0Mjk1NDYyMTM1", "number": 41, "title": "Flag Feature / Enhancement", "createdAt": "2019-07-08T19:15:07Z", "url": "https://github.com/ice1000/jimgui/pull/41", "merged": true, "comments": {"totalCount": 0}, "reviews": {"totalCount": 1}, "reviewRequests": {"totalCount": 0}, "timelineItems": {"totalCount": 1, "pageInfo": {"startCursor": "Y3Vyc29yOnYyOpPPAAABa9QQ8ugFqTI1OTIxNTEwMg==", "endCursor": "Y3Vyc29yOnYyOpPPAAABa9QQ8ugFqTI1OTIxNTEwMg==", "hasNextPage": false, "hasPreviousPage": false}, "nodes": [{"comments": {"totalCount": 0}}]}}, {"id": "MDExOlB1bGxSZXF1ZXN0Mjk1MDUzMTc4", "number": 39, "title": "Update JImStr.java", "createdAt": "2019-07-06T17:44:57Z", "url": "https://github.com/ice1000/jimgui/pull/39", "merged": true, "comments": {"totalCount": 0}, "reviews": {"totalCount": 1}, "reviewRequests": {"totalCount": 0}, "timelineItems": {"totalCount": 1, "pageInfo": {"startCursor": "Y3Vyc29yOnYyOpPPAAABa8oSL_AFqTI1ODYwNjM1MQ==", "endCursor": "Y3Vyc29yOnYyOpPPAAABa8oSL_AFqTI1ODYwNjM1MQ==", "hasNextPage": false, "hasPreviousPage": false}, "nodes": [{"comments": {"totalCount": 0}}]}}, {"id": "MDExOlB1bGxSZXF1ZXN0Mjk1MDUyNjMw", "number": 38, "title": "Couple of small changes", "createdAt": "2019-07-06T17:33:49Z", "url": "https://github.com/ice1000/jimgui/pull/38", "merged": false, "comments": {"totalCount": 1}, "reviews": {"totalCount": 0}, "reviewRequests": {"totalCount": 0}, "timelineItems": {"totalCount": 0, "pageInfo": {"startCursor": null, "endCursor": null, "hasNextPage": false, "hasPreviousPage": false}, "nodes": []}}, {"id": "MDExOlB1bGxSZXF1ZXN0Mjg1MzExNDgy", "number": 34, "title": "Add a Gitter chat badge to README.md", "createdAt": "2019-06-05T10:18:19Z", "url": "https://github.com/ice1000/jimgui/pull/34", "merged": true, "comments": {"totalCount": 0}, "reviews": {"totalCount": 0}, "reviewRequests": {"totalCount": 0}, "timelineItems": {"totalCount": 0, "pageInfo": {"startCursor": null, "endCursor": null, "hasNextPage": false, "hasPreviousPage": false}, "nodes": []}}, {"id": "MDExOlB1bGxSZXF1ZXN0Mjg1MTYzNzQ0", "number": 32, "title": "Added title to JImGui", "createdAt": "2019-06-04T22:16:03Z", "url": "https://github.com/ice1000/jimgui/pull/32", "merged": true, "comments": {"totalCount": 0}, "reviews": {"totalCount": 1}, "reviewRequests": {"totalCount": 0}, "timelineItems": {"totalCount": 1, "pageInfo": {"startCursor": "Y3Vyc29yOnYyOpPPAAABayTZOIAFqTI0NTc1MjAxMQ==", "endCursor": "Y3Vyc29yOnYyOpPPAAABayTZOIAFqTI0NTc1MjAxMQ==", "hasNextPage": false, "hasPreviousPage": false}, "nodes": [{"comments": {"totalCount": 0}}]}}, {"id": "MDExOlB1bGxSZXF1ZXN0MjU3Nzg0MzEw", "number": 26, "title": "fix openGL version for glsl 1.30", "createdAt": "2019-03-04T00:56:16Z", "url": "https://github.com/ice1000/jimgui/pull/26", "merged": true, "comments": {"totalCount": 0}, "reviews": {"totalCount": 0}, "reviewRequests": {"totalCount": 1}, "timelineItems": {"totalCount": 0, "pageInfo": {"startCursor": null, "endCursor": null, "hasNextPage": false, "hasPreviousPage": false}, "nodes": []}}, {"id": "MDExOlB1bGxSZXF1ZXN0MjU3NzAzNTcy", "number": 25, "title": "handle OSX JVM arguments in gradle script", "createdAt": "2019-03-03T00:56:48Z", "url": "https://github.com/ice1000/jimgui/pull/25", "merged": true, "comments": {"totalCount": 1}, "reviews": {"totalCount": 1}, "reviewRequests": {"totalCount": 0}, "timelineItems": {"totalCount": 1, "pageInfo": {"startCursor": "Y3Vyc29yOnYyOpPPAAABaUFzFVgFqTIwOTg5MjIyMA==", "endCursor": "Y3Vyc29yOnYyOpPPAAABaUFzFVgFqTIwOTg5MjIyMA==", "hasNextPage": false, "hasPreviousPage": false}, "nodes": [{"comments": {"totalCount": 2}}]}}, {"id": "MDExOlB1bGxSZXF1ZXN0MjU3NzAzNTQ2", "number": 24, "title": "use glsl version 1.50 on OSX", "createdAt": "2019-03-03T00:56:16Z", "url": "https://github.com/ice1000/jimgui/pull/24", "merged": true, "comments": {"totalCount": 0}, "reviews": {"totalCount": 1}, "reviewRequests": {"totalCount": 0}, "timelineItems": {"totalCount": 1, "pageInfo": {"startCursor": "Y3Vyc29yOnYyOpPPAAABaUGBF0gFqTIwOTg5MjUwNQ==", "endCursor": "Y3Vyc29yOnYyOpPPAAABaUGBF0gFqTIwOTg5MjUwNQ==", "hasNextPage": false, "hasPreviousPage": false}, "nodes": [{"comments": {"totalCount": 0}}]}}, {"id": "MDExOlB1bGxSZXF1ZXN0MjU3NzAzNTAz", "number": 23, "title": "fix missing source file in building imgui", "createdAt": "2019-03-03T00:55:10Z", "url": "https://github.com/ice1000/jimgui/pull/23", "merged": true, "comments": {"totalCount": 0}, "reviews": {"totalCount": 1}, "reviewRequests": {"totalCount": 0}, "timelineItems": {"totalCount": 1, "pageInfo": {"startCursor": "Y3Vyc29yOnYyOpPPAAABaUGBq7gFqTIwOTg5MjUyMQ==", "endCursor": "Y3Vyc29yOnYyOpPPAAABaUGBq7gFqTIwOTg5MjUyMQ==", "hasNextPage": false, "hasPreviousPage": false}, "nodes": [{"comments": {"totalCount": 0}}]}}, {"id": "MDExOlB1bGxSZXF1ZXN0MjE0NzI2NTIx", "number": 17, "title": "docs: update README", "createdAt": "2018-09-11T18:37:16Z", "url": "https://github.com/ice1000/jimgui/pull/17", "merged": true, "comments": {"totalCount": 1}, "reviews": {"totalCount": 0}, "reviewRequests": {"totalCount": 0}, "timelineItems": {"totalCount": 0, "pageInfo": {"startCursor": null, "endCursor": null, "hasNextPage": false, "hasPreviousPage": false}, "nodes": []}}, {"id": "MDExOlB1bGxSZXF1ZXN0MTkzNjA1NTY5", "number": 8, "title": "Sync imgui's API `getGlyphRangesChineseFull`", "createdAt": "2018-06-08T12:55:23Z", "url": "https://github.com/ice1000/jimgui/pull/8", "merged": true, "comments": {"totalCount": 1}, "reviews": {"totalCount": 1}, "reviewRequests": {"totalCount": 0}, "timelineItems": {"totalCount": 1, "pageInfo": {"startCursor": "Y3Vyc29yOnYyOpPPAAABY9_NWVgFqTEyNzE4NDY1Nw==", "endCursor": "Y3Vyc29yOnYyOpPPAAABY9_NWVgFqTEyNzE4NDY1Nw==", "hasNextPage": false, "hasPreviousPage": false}, "nodes": [{"comments": {"totalCount": 0}}]}}, {"id": "MDExOlB1bGxSZXF1ZXN0MTkxOTI3OTU1", "number": 7, "title": "Update CMake to make Visual Studio happy", "createdAt": "2018-06-01T03:52:07Z", "url": "https://github.com/ice1000/jimgui/pull/7", "merged": true, "comments": {"totalCount": 1}, "reviews": {"totalCount": 0}, "reviewRequests": {"totalCount": 1}, "timelineItems": {"totalCount": 0, "pageInfo": {"startCursor": null, "endCursor": null, "hasNextPage": false, "hasPreviousPage": false}, "nodes": []}}, {"id": "MDExOlB1bGxSZXF1ZXN0MTg5MjM1OTk4", "number": 5, "title": "Support Mac OS X", "createdAt": "2018-05-20T14:27:46Z", "url": "https://github.com/ice1000/jimgui/pull/5", "merged": true, "comments": {"totalCount": 1}, "reviews": {"totalCount": 0}, "reviewRequests": {"totalCount": 0}, "timelineItems": {"totalCount": 0, "pageInfo": {"startCursor": null, "endCursor": null, "hasNextPage": false, "hasPreviousPage": false}, "nodes": []}}, {"id": "MDExOlB1bGxSZXF1ZXN0MTg2NjkxMTUy", "number": 4, "title": "Appveyor", "createdAt": "2018-05-08T16:38:45Z", "url": "https://github.com/ice1000/jimgui/pull/4", "merged": true, "comments": {"totalCount": 0}, "reviews": {"totalCount": 0}, "reviewRequests": {"totalCount": 0}, "timelineItems": {"totalCount": 0, "pageInfo": {"startCursor": null, "endCursor": null, "hasNextPage": false, "hasPreviousPage": false}, "nodes": []}}, {"id": "MDExOlB1bGxSZXF1ZXN0MTg2NjQwMTQ5", "number": 3, "title": "Appveyor", "createdAt": "2018-05-08T13:48:11Z", "url": "https://github.com/ice1000/jimgui/pull/3", "merged": true, "comments": {"totalCount": 0}, "reviews": {"totalCount": 0}, "reviewRequests": {"totalCount": 0}, "timelineItems": {"totalCount": 0, "pageInfo": {"startCursor": null, "endCursor": null, "hasNextPage": false, "hasPreviousPage": false}, "nodes": []}}, {"id": "MDExOlB1bGxSZXF1ZXN0MTg1MTI5Njg4", "number": 1, "title": "Circleci", "createdAt": "2018-05-01T06:45:00Z", "url": "https://github.com/ice1000/jimgui/pull/1", "merged": true, "comments": {"totalCount": 0}, "reviews": {"totalCount": 0}, "reviewRequests": {"totalCount": 0}, "timelineItems": {"totalCount": 0, "pageInfo": {"startCursor": null, "endCursor": null, "hasNextPage": false, "hasPreviousPage": false}, "nodes": []}}]}, "rateLimit": {"limit": 5000, "remaining": 4097, "cost": 1, "resetAt": "2021-10-17T12:14:28Z"}}}