{"data": {"search": {"issueCount": 16, "pageInfo": {"startCursor": "Y3Vyc29yOjE=", "endCursor": "Y3Vyc29yOjE2", "hasNextPage": false, "hasPreviousPage": false}, "nodes": [{"id": "MDExOlB1bGxSZXF1ZXN0MjI1NTUzNzI=", "number": 22, "title": "Update de_DE.lang", "createdAt": "2014-10-10T11:53:44Z", "url": "https://github.com/iChun/Photoreal/pull/22", "merged": true, "comments": {"totalCount": 0}, "reviews": {"totalCount": 0}, "reviewRequests": {"totalCount": 0}, "timelineItems": {"totalCount": 0, "pageInfo": {"startCursor": null, "endCursor": null, "hasNextPage": false, "hasPreviousPage": false}, "nodes": []}}, {"id": "MDExOlB1bGxSZXF1ZXN0MjIzMjg0NTU=", "number": 21, "title": "Create fr_FR.lang", "createdAt": "2014-10-07T03:02:30Z", "url": "https://github.com/iChun/Photoreal/pull/21", "merged": true, "comments": {"totalCount": 1}, "reviews": {"totalCount": 0}, "reviewRequests": {"totalCount": 0}, "timelineItems": {"totalCount": 0, "pageInfo": {"startCursor": null, "endCursor": null, "hasNextPage": false, "hasPreviousPage": false}, "nodes": []}}, {"id": "MDExOlB1bGxSZXF1ZXN0MjE5MDAyNDU=", "number": 20, "title": "Update and rename ru_RU to ru_RU.lang", "createdAt": "2014-09-28T10:05:52Z", "url": "https://github.com/iChun/Photoreal/pull/20", "merged": true, "comments": {"totalCount": 0}, "reviews": {"totalCount": 0}, "reviewRequests": {"totalCount": 0}, "timelineItems": {"totalCount": 0, "pageInfo": {"startCursor": null, "endCursor": null, "hasNextPage": false, "hasPreviousPage": false}, "nodes": []}}, {"id": "MDExOlB1bGxSZXF1ZXN0MjE3MzQ1MzU=", "number": 19, "title": "Update de_DE.lang", "createdAt": "2014-09-24T18:31:54Z", "url": "https://github.com/iChun/Photoreal/pull/19", "merged": true, "comments": {"totalCount": 0}, "reviews": {"totalCount": 0}, "reviewRequests": {"totalCount": 0}, "timelineItems": {"totalCount": 0, "pageInfo": {"startCursor": null, "endCursor": null, "hasNextPage": false, "hasPreviousPage": false}, "nodes": []}}, {"id": "MDExOlB1bGxSZXF1ZXN0MTk4MjIwMjQ=", "number": 18, "title": "Create pt_BR.lang", "createdAt": "2014-08-14T23:29:49Z", "url": "https://github.com/iChun/Photoreal/pull/18", "merged": true, "comments": {"totalCount": 0}, "reviews": {"totalCount": 0}, "reviewRequests": {"totalCount": 0}, "timelineItems": {"totalCount": 0, "pageInfo": {"startCursor": null, "endCursor": null, "hasNextPage": false, "hasPreviousPage": false}, "nodes": []}}, {"id": "MDExOlB1bGxSZXF1ZXN0MTk2MDgxMzY=", "number": 16, "title": "Created es_ES.lang translation file.", "createdAt": "2014-08-11T15:33:37Z", "url": "https://github.com/iChun/Photoreal/pull/16", "merged": true, "comments": {"totalCount": 0}, "reviews": {"totalCount": 0}, "reviewRequests": {"totalCount": 0}, "timelineItems": {"totalCount": 0, "pageInfo": {"startCursor": null, "endCursor": null, "hasNextPage": false, "hasPreviousPage": false}, "nodes": []}}, {"id": "MDExOlB1bGxSZXF1ZXN0MTkzMzYzNzI=", "number": 15, "title": "Update de_DE.lang", "createdAt": "2014-08-05T11:30:50Z", "url": "https://github.com/iChun/Photoreal/pull/15", "merged": true, "comments": {"totalCount": 0}, "reviews": {"totalCount": 0}, "reviewRequests": {"totalCount": 0}, "timelineItems": {"totalCount": 0, "pageInfo": {"startCursor": null, "endCursor": null, "hasNextPage": false, "hasPreviousPage": false}, "nodes": []}}, {"id": "MDExOlB1bGxSZXF1ZXN0MTkyNTI2MDE=", "number": 14, "title": "Created the Spanish (Uruguay) Translation", "createdAt": "2014-08-03T05:04:13Z", "url": "https://github.com/iChun/Photoreal/pull/14", "merged": true, "comments": {"totalCount": 0}, "reviews": {"totalCount": 0}, "reviewRequests": {"totalCount": 0}, "timelineItems": {"totalCount": 0, "pageInfo": {"startCursor": null, "endCursor": null, "hasNextPage": false, "hasPreviousPage": false}, "nodes": []}}, {"id": "MDExOlB1bGxSZXF1ZXN0MTkyNTE0Mjk=", "number": 13, "title": "Create es_AR.lang", "createdAt": "2014-08-03T01:18:16Z", "url": "https://github.com/iChun/Photoreal/pull/13", "merged": true, "comments": {"totalCount": 0}, "reviews": {"totalCount": 0}, "reviewRequests": {"totalCount": 0}, "timelineItems": {"totalCount": 0, "pageInfo": {"startCursor": null, "endCursor": null, "hasNextPage": false, "hasPreviousPage": false}, "nodes": []}}, {"id": "MDExOlB1bGxSZXF1ZXN0MTg5NTk5Nzk=", "number": 12, "title": "Russian version of mod.", "createdAt": "2014-07-28T10:41:29Z", "url": "https://github.com/iChun/Photoreal/pull/12", "merged": true, "comments": {"totalCount": 0}, "reviews": {"totalCount": 0}, "reviewRequests": {"totalCount": 0}, "timelineItems": {"totalCount": 0, "pageInfo": {"startCursor": null, "endCursor": null, "hasNextPage": false, "hasPreviousPage": false}, "nodes": []}}, {"id": "MDExOlB1bGxSZXF1ZXN0MTg5MzEzMDM=", "number": 11, "title": "Update de_DE.lang - Photoreal", "createdAt": "2014-07-26T12:21:20Z", "url": "https://github.com/iChun/Photoreal/pull/11", "merged": true, "comments": {"totalCount": 0}, "reviews": {"totalCount": 0}, "reviewRequests": {"totalCount": 0}, "timelineItems": {"totalCount": 0, "pageInfo": {"startCursor": null, "endCursor": null, "hasNextPage": false, "hasPreviousPage": false}, "nodes": []}}, {"id": "MDExOlB1bGxSZXF1ZXN0MTg1MjA3NDA=", "number": 9, "title": "Create hu_HU.lang", "createdAt": "2014-07-17T10:41:04Z", "url": "https://github.com/iChun/Photoreal/pull/9", "merged": true, "comments": {"totalCount": 0}, "reviews": {"totalCount": 0}, "reviewRequests": {"totalCount": 0}, "timelineItems": {"totalCount": 0, "pageInfo": {"startCursor": null, "endCursor": null, "hasNextPage": false, "hasPreviousPage": false}, "nodes": []}}, {"id": "MDExOlB1bGxSZXF1ZXN0MTg0MzcxOTE=", "number": 8, "title": "Danish", "createdAt": "2014-07-15T21:46:15Z", "url": "https://github.com/iChun/Photoreal/pull/8", "merged": true, "comments": {"totalCount": 0}, "reviews": {"totalCount": 0}, "reviewRequests": {"totalCount": 0}, "timelineItems": {"totalCount": 0, "pageInfo": {"startCursor": null, "endCursor": null, "hasNextPage": false, "hasPreviousPage": false}, "nodes": []}}, {"id": "MDExOlB1bGxSZXF1ZXN0MTgzMzYyOTQ=", "number": 7, "title": "Revert \"Dutch translation of Photoreal\"", "createdAt": "2014-07-14T08:18:34Z", "url": "https://github.com/iChun/Photoreal/pull/7", "merged": true, "comments": {"totalCount": 0}, "reviews": {"totalCount": 0}, "reviewRequests": {"totalCount": 0}, "timelineItems": {"totalCount": 0, "pageInfo": {"startCursor": null, "endCursor": null, "hasNextPage": false, "hasPreviousPage": false}, "nodes": []}}, {"id": "MDExOlB1bGxSZXF1ZXN0MTgzMjY1MDY=", "number": 6, "title": "Dutch translation of Photoreal", "createdAt": "2014-07-13T20:08:19Z", "url": "https://github.com/iChun/Photoreal/pull/6", "merged": true, "comments": {"totalCount": 1}, "reviews": {"totalCount": 0}, "reviewRequests": {"totalCount": 0}, "timelineItems": {"totalCount": 0, "pageInfo": {"startCursor": null, "endCursor": null, "hasNextPage": false, "hasPreviousPage": false}, "nodes": []}}, {"id": "MDExOlB1bGxSZXF1ZXN0MTgyOTU2MTg=", "number": 4, "title": "Create de_DE.lang", "createdAt": "2014-07-11T19:00:14Z", "url": "https://github.com/iChun/Photoreal/pull/4", "merged": true, "comments": {"totalCount": 0}, "reviews": {"totalCount": 0}, "reviewRequests": {"totalCount": 0}, "timelineItems": {"totalCount": 0, "pageInfo": {"startCursor": null, "endCursor": null, "hasNextPage": false, "hasPreviousPage": false}, "nodes": []}}]}, "rateLimit": {"limit": 5000, "remaining": 4080, "cost": 1, "resetAt": "2021-10-17T12:14:28Z"}}}