{"data": {"repository": {"pullRequest": {"id": "MDExOlB1bGxSZXF1ZXN0NTAwMzQ2NzI0", "number": 12206, "title": "[DOCFIX] Update performance tuning documentation", "bodyText": "", "createdAt": "2020-10-09T05:05:24Z", "url": "https://github.com/Alluxio/alluxio/pull/12206", "merged": true, "mergeCommit": {"oid": "57c9b33aef09164ebff5fd086145fd5e8d10d0d1"}, "closed": true, "closedAt": "2020-10-14T20:23:37Z", "author": {"login": "ZacBlanco"}, "timelineItems": {"totalCount": 3, "pageInfo": {"startCursor": "Y3Vyc29yOnYyOpPPAAABdQu_FtAH2gAyNTAwMzQ2NzI0OjRhODJiYjQxMzFmMTllOTcxY2E5YTVhZmVkMmU0ZmM2MjFhZWFmYWI=", "endCursor": "Y3Vyc29yOnYyOpPPAAABdSjLSsgFqTUwODcwMjUyNA==", "hasNextPage": false, "hasPreviousPage": false}, "nodes": [{"__typename": "PullRequestCommit", "commit": {"oid": "4a82bb4131f19e971ca9a5afed2e4fc621aeafab", "author": {"user": {"login": "ZacBlanco", "name": "Zac Blanco"}}, "url": "https://github.com/Alluxio/alluxio/commit/4a82bb4131f19e971ca9a5afed2e4fc621aeafab", "committedDate": "2020-10-09T05:04:34Z", "message": "Update performance tuning documentation"}}, {"__typename": "PullRequestReview", "id": "MDE3OlB1bGxSZXF1ZXN0UmV2aWV3NTA4Njc4NDIz", "url": "https://github.com/Alluxio/alluxio/pull/12206#pullrequestreview-508678423", "createdAt": "2020-10-14T19:52:11Z", "commit": {"oid": "4a82bb4131f19e971ca9a5afed2e4fc621aeafab"}, "state": "APPROVED", "comments": {"totalCount": 0, "pageInfo": {"startCursor": null, "endCursor": null, "hasNextPage": false, "hasPreviousPage": false}, "nodes": []}}, {"__typename": "PullRequestReview", "id": "MDE3OlB1bGxSZXF1ZXN0UmV2aWV3NTA4NzAyNTI0", "url": "https://github.com/Alluxio/alluxio/pull/12206#pullrequestreview-508702524", "createdAt": "2020-10-14T20:26:52Z", "commit": {"oid": "4a82bb4131f19e971ca9a5afed2e4fc621aeafab"}, "state": "COMMENTED", "comments": {"totalCount": 1, "pageInfo": {"startCursor": "Y3Vyc29yOnYyOpK0MjAyMC0xMC0xNFQyMDoyNjo1M1rOHhj02g==", "endCursor": "Y3Vyc29yOnYyOpK0MjAyMC0xMC0xNFQyMDoyNjo1M1rOHhj02g==", "hasNextPage": false, "hasPreviousPage": false}, "nodes": [{"id": "MDI0OlB1bGxSZXF1ZXN0UmV2aWV3Q29tbWVudDUwNDk1MjAyNg==", "bodyText": "@ZacBlanco @gpang Could we include where the user can find these messages?", "url": "https://github.com/Alluxio/alluxio/pull/12206#discussion_r504952026", "createdAt": "2020-10-14T20:26:53Z", "author": {"login": "calvinjia"}, "path": "docs/en/operation/Performance-Tuning.md", "diffHunk": "@@ -80,8 +86,10 @@ Also check out the [metrics system][2] for better insight in how the Alluxio ser\n \n To detect long GC pauses, Alluxio administrators can set `alluxio.master.jvm.monitor.enabled=true`\n for masters or `alluxio.worker.jvm.monitor.enabled=true` for workers.\n+They are enabled by default in Alluxio 2.4.0 and newer.", "state": "SUBMITTED", "replyTo": null, "originalCommit": {"oid": "4a82bb4131f19e971ca9a5afed2e4fc621aeafab"}, "originalPosition": 17}]}}]}}}, "rateLimit": {"limit": 5000, "remaining": 3518, "cost": 1, "resetAt": "2021-10-29T17:30:11Z"}}}