{"pr_number": 3439, "pr_title": "Issue/3274 filter report list by type", "pr_createdAt": "2020-02-24T23:49:12Z", "pr_url": "https://github.com/akvo/akvo-flow/pull/3439", "timeline": [{"oid": "880ca9502cb7fcbbb3f628d502d17b1fbbd467fb", "url": "https://github.com/akvo/akvo-flow/commit/880ca9502cb7fcbbb3f628d502d17b1fbbd467fb", "message": "[#3274]Add user filter, guard against NPEs", "committedDate": "2020-02-20T12:08:48Z", "type": "commit"}, {"oid": "ea79cf900e124f92c27df07450624300bad56222", "url": "https://github.com/akvo/akvo-flow/commit/ea79cf900e124f92c27df07450624300bad56222", "message": "[#3274]Fix empty parameter check. Remove unused stuff.", "committedDate": "2020-02-21T15:24:27Z", "type": "commit"}, {"oid": "039b70c745886b3aba9c1b76c20113b8046387e5", "url": "https://github.com/akvo/akvo-flow/commit/039b70c745886b3aba9c1b76c20113b8046387e5", "message": "[#3274]Update copyright year. Remove unused stuff.", "committedDate": "2020-02-21T15:26:31Z", "type": "commit"}, {"id": "MDI0OlB1bGxSZXF1ZXN0UmV2aWV3Q29tbWVudDM4Mzc3NTYzMg==", "url": "https://github.com/akvo/akvo-flow/pull/3439#discussion_r383775632", "bodyText": "Why don't we just pass empty string and then check for empty in the method that uses it?", "author": "valllllll2000", "createdAt": "2020-02-25T10:02:04Z", "path": "GAE/src/org/akvo/flow/rest/ReportRestService.java", "diffHunk": "@@ -123,10 +123,17 @@ private boolean isAdminRole() {\n     // find all reports belonging to the current user\n     @RequestMapping(method = RequestMethod.GET, value = \"\")\n     @ResponseBody\n-    public Map<String, Object> listMyReports() {\n+    public Map<String, Object> listMyReports(\n+            @RequestParam(value = \"reportType\", defaultValue = \"\") String reportType\n+            ) {\n         final Map<String, Object> response = new HashMap<String, Object>();\n         List<ReportDto> results = new ArrayList<ReportDto>();\n-        List<Report> reports = reportDao.listAllByCurrentUser();\n+        List<Report> reports;\n+        if (reportType.equals(\"\")) { //Cannot have null as the defaultValue\n+            reportType = null;", "originalCommit": "039b70c745886b3aba9c1b76c20113b8046387e5", "replyToReviewId": null, "replies": [{"id": "MDI0OlB1bGxSZXF1ZXN0UmV2aWV3Q29tbWVudDM4MzgxODc5Nw==", "url": "https://github.com/akvo/akvo-flow/pull/3439#discussion_r383818797", "bodyText": "Just for consistency. In most places we pass null to the dao methods to indicate a param should be ignored.", "author": "stellanl", "createdAt": "2020-02-25T11:22:59Z", "replyToReviewId": "MDI0OlB1bGxSZXF1ZXN0UmV2aWV3Q29tbWVudDM4Mzc3NTYzMg=="}], "type": "inlineReview"}]}